{
  "bar.customModules.storage.paths": [
    "/"
  ],
  "theme.font.name": "Iosevka Nerd Font",
  "theme.font.style": "oblique",
  "theme.font.label": "Iosevka Nerd Font Ultra-Light Oblique",
  "theme.font.size": "1rem",
  "theme.font.weight": 500,
  "terminal": "wezterm",
  "menus.transition": "crossfade",
  "theme.bar.menus.enableShadow": false,
  "scalingPriority": "hyprland",
  "theme.bar.menus.monochrome": true,
  "theme.bar.floating": true,
  "theme.bar.location": "top",
  "theme.bar.buttons.borderSize": "0.1em",
  "theme.bar.buttons.enableBorders": false,
  "theme.bar.border.location": "none",
  "theme.bar.enableShadow": true,
  "bar.launcher.autoDetectIcon": true,
  "theme.bar.buttons.dashboard.enableBorder": true,
  "theme.bar.buttons.workspaces.enableBorder": true,
  "bar.workspaces.monitorSpecific": true,
  "bar.workspaces.show_icons": false,
  "bar.workspaces.show_numbered": false,
  "bar.workspaces.workspaceMask": false,
  "bar.workspaces.showWsIcons": false,
  "bar.workspaces.applicationIconOncePerWorkspace": true,
  "bar.workspaces.showApplicationIcons": false,
  "bar.workspaces.numbered_active_indicator": "underline",
  "theme.bar.buttons.windowtitle.enableBorder": true,
  "bar.windowtitle.custom_title": true,
  "bar.windowtitle.icon": true,
  "bar.windowtitle.label": true,
  "bar.windowtitle.class_name": true,
  "theme.bar.buttons.volume.enableBorder": true,
  "theme.bar.buttons.network.enableBorder": true,
  "bar.network.label": false,
  "bar.network.showWifiInfo": true,
  "theme.bar.buttons.bluetooth.enableBorder": true,
  "bar.bluetooth.label": false,
  "theme.bar.buttons.battery.enableBorder": true,
  "bar.battery.hideLabelWhenFull": false,
  "bar.battery.label": true,
  "theme.bar.buttons.systray.enableBorder": true,
  "theme.bar.buttons.clock.enableBorder": true,
  "bar.clock.format": "%a %d %b  %I:%M:%S %p",
  "bar.clock.showTime": true,
  "bar.clock.showIcon": true,
  "theme.bar.buttons.media.enableBorder": true,
  "bar.media.show_label": true,
  "bar.media.truncation": false,
  "bar.media.show_active_only": true,
  "theme.bar.buttons.notifications.enableBorder": true,
  "bar.notifications.show_total": false,
  "bar.notifications.hideCountWhenZero": false,
  "menus.media.hideAuthor": false,
  "menus.media.hideAlbum": false,
  "menus.media.displayTime": false,
  "bar.media.truncation_size": 60,
  "menus.media.displayTimeTooltip": false,
  "theme.notification.enableShadow": false,
  "notifications.monitor": 1,
  "notifications.autoDismiss": true,
  "theme.osd.enable": true,
  "menus.clock.time.military": false,
  "menus.clock.weather.location": "Los Angeles",
  "menus.clock.weather.enabled": false,
  "menus.clock.weather.unit": "metric",
  "menus.dashboard.powermenu.avatar.image": "/usr/share/endeavouros/EndeavourOS-icon.png",
  "theme.bar.buttons.modules.microphone.enableBorder": true,
  "theme.bar.buttons.modules.ram.enableBorder": true,
  "theme.bar.buttons.modules.cpu.enableBorder": true,
  "theme.bar.buttons.modules.cpuTemp.enableBorder": true,
  "theme.bar.buttons.modules.storage.enableBorder": true,
  "theme.bar.buttons.modules.netstat.enableBorder": true,
  "theme.bar.buttons.modules.kbLayout.enableBorder": true,
  "theme.bar.buttons.modules.updates.enableBorder": true,
  "theme.bar.buttons.modules.submap.enableBorder": true,
  "bar.customModules.weather.unit": "metric",
  "theme.bar.buttons.modules.weather.enableBorder": true,
  "theme.bar.buttons.modules.hyprsunset.enableBorder": true,
  "theme.bar.buttons.modules.hypridle.enableBorder": true,
  "theme.bar.buttons.modules.cava.enableBorder": true,
  "theme.bar.buttons.modules.worldclock.enableBorder": true,
  "theme.bar.buttons.modules.power.enableBorder": true,
  "wallpaper.image": "/home/arp/Downloads/endeavourcatpuccin-1920x1080.png",
  "theme.bar.transparent": true,
  "theme.bar.shadow": "0px 1px 3px 2px #16161e",
  "menus.dashboard.shortcuts.left.shortcut1.icon": "",
  "menus.dashboard.shortcuts.left.shortcut1.tooltip": "Zen Browser",
  "menus.dashboard.shortcuts.left.shortcut1.command": "zen-browser",
  "menus.dashboard.shortcuts.left.shortcut4.command": "steam",
  "menus.dashboard.shortcuts.left.shortcut3.command": "signal-desktop",
  "menus.dashboard.shortcuts.left.shortcut3.tooltip": "Signal",
  "menus.dashboard.shortcuts.left.shortcut3.icon": "󰭹",
  "menus.dashboard.shortcuts.left.shortcut4.tooltip": "Steam",
  "menus.dashboard.shortcuts.left.shortcut4.icon": ""
}